aliyunsdkpolardbx/__init__.py
aliyunsdkpolardbx/endpoint.py
aliyunsdkpolardbx/request/__init__.py
aliyunsdkpolardbx/request/v20200202/AlignStoragePrimaryAzoneRequest.py
aliyunsdkpolardbx/request/v20200202/AllocateColdDataVolumeRequest.py
aliyunsdkpolardbx/request/v20200202/AllocateInstancePublicConnectionRequest.py
aliyunsdkpolardbx/request/v20200202/CancelActiveOperationTasksRequest.py
aliyunsdkpolardbx/request/v20200202/ChangeResourceGroupRequest.py
aliyunsdkpolardbx/request/v20200202/CheckCloudResourceAuthorizedRequest.py
aliyunsdkpolardbx/request/v20200202/CreateAccountRequest.py
aliyunsdkpolardbx/request/v20200202/CreateBackupRequest.py
aliyunsdkpolardbx/request/v20200202/CreateDBInstanceRequest.py
aliyunsdkpolardbx/request/v20200202/CreateDBRequest.py
aliyunsdkpolardbx/request/v20200202/CreateSuperAccountRequest.py
aliyunsdkpolardbx/request/v20200202/DeleteAccountRequest.py
aliyunsdkpolardbx/request/v20200202/DeleteDBInstanceRequest.py
aliyunsdkpolardbx/request/v20200202/DeleteDBRequest.py
aliyunsdkpolardbx/request/v20200202/DescribeAccountListRequest.py
aliyunsdkpolardbx/request/v20200202/DescribeActiveOperationMaintainConfRequest.py
aliyunsdkpolardbx/request/v20200202/DescribeActiveOperationTaskCountRequest.py
aliyunsdkpolardbx/request/v20200202/DescribeActiveOperationTasksRequest.py
aliyunsdkpolardbx/request/v20200202/DescribeArchiveTableListRequest.py
aliyunsdkpolardbx/request/v20200202/DescribeBackupPolicyRequest.py
aliyunsdkpolardbx/request/v20200202/DescribeBackupSetListRequest.py
aliyunsdkpolardbx/request/v20200202/DescribeBackupSetRequest.py
aliyunsdkpolardbx/request/v20200202/DescribeBinaryLogListRequest.py
aliyunsdkpolardbx/request/v20200202/DescribeCharacterSetRequest.py
aliyunsdkpolardbx/request/v20200202/DescribeColdDataBasicInfoRequest.py
aliyunsdkpolardbx/request/v20200202/DescribeDBInstanceAttributeRequest.py
aliyunsdkpolardbx/request/v20200202/DescribeDBInstanceConfigRequest.py
aliyun_python_sdk_polardbx-1.1.5.dist-info/LICENSE
aliyun_python_sdk_polardbx-1.1.5.dist-info/METADATA
aliyun_python_sdk_polardbx-1.1.5.dist-info/WHEEL
aliyun_python_sdk_polardbx-1.1.5.dist-info/top_level.txt
aliyun_python_sdk_polardbx-1.1.5.dist-info/RECORD
